tank_wars_iit/__init__.py
tank_wars_iit/_engine/__init__.py
tank_wars_iit/_engine/arena.py
tank_wars_iit/_engine/control.py
tank_wars_iit/_engine/map.py
tank_wars_iit/_engine/pathfinding.py
tank_wars_iit/_engine/quadtree.py
tank_wars_iit/_engine/robotlist.py
tank_wars_iit/_engine/entity/__init__.py
tank_wars_iit/_engine/entity/bullet.py
tank_wars_iit/_engine/entity/coin.py
tank_wars_iit/_engine/entity/entity.py
tank_wars_iit/_engine/entity/robot.py
tank_wars_iit/_engine/entity/wall.py
tank_wars_iit/_engine/maps/basic.json
tank_wars_iit/_engine/maps/circles.json
tank_wars_iit/_engine/maps/circles_large.json
tank_wars_iit/_engine/maps/lock.json
tank_wars_iit/_engine/maps/maze.json
tank_wars_iit/_engine/maps/stress_test.json
tank_wars_iit/_engine/util/__init__.py
tank_wars_iit/_engine/util/draw.py
tank_wars_iit/_engine/util/geometry.py
tank_wars_iit/examples/__init__.py
tank_wars_iit/examples/controllers.py
tank_wars_iit/scenario/__init__.py
tank_wars_iit/scenario/battleroyale.py
tank_wars_iit/scenario/onevsone.py
tank_wars_iit/scenario/tournament.py
tank_wars_iit/util/__init__.py
tank_wars_iit-1.0.2.dist-info/LICENSE
tank_wars_iit-1.0.2.dist-info/METADATA
tank_wars_iit-1.0.2.dist-info/WHEEL
tank_wars_iit-1.0.2.dist-info/top_level.txt
tank_wars_iit-1.0.2.dist-info/RECORD
