Metadata-Version: 2.1
Name: tank-wars-iit
Version: 1.0.2
Summary: Tank Wars framework for Scarlet HackNiite
Author-email: Association for Computing Machinery at the Illinois Institute of Technology <acm@iit.edu>, Tommy Vadakumchery <t.vadakumchery1@gmail.com>
Project-URL: Homepage, https://github.com/acm-iit/robot-wars
Project-URL: Bug Tracker, https://github.com/acm-iit/robot-wars/issues
Classifier: Programming Language :: Python :: 3
Classifier: Programming Language :: Python :: 3.10
Classifier: License :: OSI Approved :: MIT License
Classifier: Operating System :: OS Independent
Requires-Python: >=3.10
License-File: LICENSE
Requires-Dist: pygame (>=2.3.0)
